{
	"info": {
		"_postman_id": "a4f2140e-5807-4227-811d-7a13a9387dce",
		"name": "TaskFlow",
		"schema": "https://schema.getpostman.com/json/collection/v2.1.0/collection.json",
		"_exporter_id": "42509057"
	},
	"item": [
		{
			"name": "Administrador",
			"item": [
				{
					"name": "Probar",
					"request": {
						"method": "GET",
						"header": [],
						"url": {
							"raw": "{{baseUrl}}/ping",
							"host": [
								"{{baseUrl}}"
							],
							"path": [
								"ping"
							]
						}
					},
					"response": []
				},
				{
					"name": "RegistrarAdmin",
					"request": {
						"method": "POST",
						"header": [
							{
								"key": "Content-Type",
								"value": "application/json",
								"type": "text"
							}
						],
						"body": {
							"mode": "raw",
							"raw": "{\r\n  \"email\": \"admin@taskflow.com\",\r\n  \"password\": \"admin123\",\r\n  \"name\": \"Administrador\",\r\n  \"role\": \"admin\"\r\n}",
							"options": {
								"raw": {
									"language": "json"
								}
							}
						},
						"url": {
							"raw": "{{baseUrl}}/api/users/register",
							"host": [
								"{{baseUrl}}"
							],
							"path": [
								"api",
								"users",
								"register"
							]
						}
					},
					"response": []
				},
				{
					"name": "RegistrarDesarrollador",
					"request": {
						"method": "POST",
						"header": [
							{
								"key": "Content-Type",
								"value": "application/json",
								"type": "text"
							}
						],
						"body": {
							"mode": "raw",
							"raw": "{\r\n  \"email\": \"dev1@taskflow.com\",\r\n  \"password\": \"dev123\",\r\n  \"name\": \"Desarrollador 1\",\r\n  \"role\": \"developer\"\r\n}",
							"options": {
								"raw": {
									"language": "json"
								}
							}
						},
						"url": {
							"raw": "{{baseUrl}}/api/users/register",
							"host": [
								"{{baseUrl}}"
							],
							"path": [
								"api",
								"users",
								"register"
							]
						}
					},
					"response": []
				},
				{
					"name": "LoginAdmin",
					"request": {
						"method": "POST",
						"header": [
							{
								"key": "Content-Type",
								"value": "application/json",
								"type": "text"
							}
						],
						"body": {
							"mode": "raw",
							"raw": "{\r\n  \"email\": \"admin@taskflow.com\",\r\n  \"password\": \"admin123\"\r\n}",
							"options": {
								"raw": {
									"language": "json"
								}
							}
						},
						"url": {
							"raw": "{{baseUrl}}/api/users/login",
							"host": [
								"{{baseUrl}}"
							],
							"path": [
								"api",
								"users",
								"login"
							]
						}
					},
					"response": []
				},
				{
					"name": "ObtenerUsuarios",
					"request": {
						"method": "GET",
						"header": [
							{
								"key": "Authorization",
								"value": "Bearer {{authToken}}",
								"type": "text"
							}
						],
						"url": {
							"raw": "{{baseUrl}}/api/users",
							"host": [
								"{{baseUrl}}"
							],
							"path": [
								"api",
								"users"
							]
						}
					},
					"response": []
				},
				{
					"name": "ObtenerUsuariosID",
					"request": {
						"method": "GET",
						"header": [
							{
								"key": "Authorization",
								"value": "Bearer {{authToken}}",
								"type": "text"
							}
						],
						"url": {
							"raw": "{{baseUrl}}/api/users/2",
							"host": [
								"{{baseUrl}}"
							],
							"path": [
								"api",
								"users",
								"2"
							]
						}
					},
					"response": []
				},
				{
					"name": "ActualizaUsuario",
					"request": {
						"method": "PUT",
						"header": [
							{
								"key": "Authorization",
								"value": "Bearer {{authToken}}",
								"type": "text"
							}
						],
						"body": {
							"mode": "raw",
							"raw": "{\r\n  \"name\": \"Desarrollador Actualizado\",\r\n  \"email\": \"dev_updated@taskflow.com\"\r\n}",
							"options": {
								"raw": {
									"language": "json"
								}
							}
						},
						"url": {
							"raw": "{{baseUrl}}/api/users/3",
							"host": [
								"{{baseUrl}}"
							],
							"path": [
								"api",
								"users",
								"3"
							]
						}
					},
					"response": []
				},
				{
					"name": "EliminarUsuario",
					"request": {
						"method": "DELETE",
						"header": [
							{
								"key": "Authorization",
								"value": "Bearer {{authToken}}",
								"type": "text"
							}
						],
						"body": {
							"mode": "raw",
							"raw": "{\r\n  \"name\": \"Desarrollador Actualizado\",\r\n  \"email\": \"dev_updated@taskflow.com\"\r\n}",
							"options": {
								"raw": {
									"language": "json"
								}
							}
						},
						"url": {
							"raw": "{{baseUrl}}/api/users/2",
							"host": [
								"{{baseUrl}}"
							],
							"path": [
								"api",
								"users",
								"2"
							]
						}
					},
					"response": []
				}
			]
		},
		{
			"name": "Desarrollador",
			"item": [
				{
					"name": "LoginDesarrollador",
					"request": {
						"method": "POST",
						"header": [
							{
								"key": "Content-Type",
								"value": "application/json",
								"type": "text"
							}
						],
						"body": {
							"mode": "raw",
							"raw": "{\r\n  \"email\": \"dev1@taskflow.com\",\r\n  \"password\": \"dev123\"\r\n}",
							"options": {
								"raw": {
									"language": "json"
								}
							}
						},
						"url": {
							"raw": "{{baseUrl}}/api/users/login",
							"host": [
								"{{baseUrl}}"
							],
							"path": [
								"api",
								"users",
								"login"
							]
						}
					},
					"response": []
				},
				{
					"name": "PruebaError",
					"request": {
						"method": "GET",
						"header": [
							{
								"key": "Authorization",
								"value": "Bearer {{tokenDev}}",
								"type": "text"
							}
						],
						"url": {
							"raw": "{{baseUrl}}/api/users",
							"host": [
								"{{baseUrl}}"
							],
							"path": [
								"api",
								"users"
							]
						}
					},
					"response": []
				}
			]
		}
	]
}